Workbook

Sheet Setup
A1: Category | B1: Monthly Budget (₦
A2: Rent | B2: 30000
A3: Food | B3: 50000
A4: Transport | B4: 45000
A5: Utilities | B5: -
A6: Data | B6: 2000
A7: Entertainment | B7: 4500
A8: Investment | B8: 10000
A9: Parents | B9: 10000
A10: Savings | B10: 0
A11: Others | B11: -

Sheet Pivot analysis
A1: Type | B1: (All)
A3: Row Labels | B3: Sum of Amount
A4: Data | B4: 17200
A5: Entertainment | B5: 20000
A6: Food | B6: 89160
A7: Investment | B7: 5000
A8: Others | B8: 325600
A9: Parents | B9: 10000
A10: Rent | B10: 30000
A11: Transport | B11: 31600
A12: Utilities | B12: 28700
A13: Grand Total | B13: 557260

Sheet Dashboard Analysis
A1: FINANCIAL DASHBOARD
T30: NET BALANCE | V30: =Summary!B18 -> 3440
S35: Underutilized | V35: Overutilized
S36: Category | T36: Unused amount | V36: Category | W36: Overused amount
S37: Transport | T37: 13400 | V37: Food | W37: -20860
S38: Investment | T38: 5000 | V38: Utilities | W38: -27700
V39: Data | W39: -15200
V40: Entertainment | W40: -15500
V41: Others | W41: -43500

Sheet Transaction
A1: Date | B1: Description | C1: Category | D1: Type | E1: Amount
A2: 19/12/2025 | B2: Salary | C2: Others | D2: Income | E2: 200000
A3: 19/12/2025 | B3: Food payment | C3: Food | D3: Expense | E3: 1560
A4: 19/12/2026 | B4: Barbing | C4: Utilities | D4: Expense | E4: 1000
A5: 21/12/2025 | B5: Rent Payment | C5: Rent | D5: Expense | E5: 30000
A6: 21/12/2025 | B6: Food payment | C6: Food | D6: Expense | E6: 2000
A7: 21/12/2025 | B7: Dash(Chinaza) | C7: Others | D7: Expense | E7: 10000
A8: 21/12/2025 | B8: Withdrawal | C8: Transport | D8: Expense | E8: 10000
A9: 21/12/2025 | B9: Food payment | C9: Food | D9: Expense | E9: 2300
A10: 21/12/2025 | B10: Food payment | C10: Food | D10: Expense | E10: 6000
A11: 21/12/2025 | B11: Food payment | C11: Food | D11: Expense | E11: 2600
A12: 21/12/2025 | B12: Food payment | C12: Food | D12: Income | E12: 5800
A13: 21/12/2025 | B13: Food payment | C13: Food | D13: Expense | E13: 3000
... A37: 31/12/2025 | B37: airtime | C37: Data | D37: Expense | E37: 1500
A38: 46023 | B38: airtime | C38: Data | D38: Expense | E38: 1000
A39: 46054 | B39: Food payment | C39: Food | D39: Expense | E39: 2100
A40: 45689 | B40: Dash(Chinaza) | C40: Others | D40: Expense | E40: 5000
A41: 46054 | B41: Barbing | C41: Utilities | D41: Expense | E41: 1500
A42: 46113 | B42: Food payment | C42: Food | D42: Expense | E42: 2200
A43: 46113 | B43: Dash(Chinaza) | C43: Others | D43: Expense | E43: 4000
A44: 46113 | B44: Food payment | C44: Food | D44: Expense | E44: 4200
A45: 46113 | B45: airtime | C45: Data | D45: Expense | E45: 6000
A46: 46113 | B46: Food payment | C46: Food | D46: Expense | E46: 2200
A47: 46143 | B47: Food payment | C47: Food | D47: Expense | E47: 1000
A48: 46143 | B48: Key duplicate | C48: Utilities | D48: Expense | E48: 2000
A49: 46143 | B49: Withdrawal | C49: Transport | D49: Expense | E49: 5200
... A61: 46357 | B61: Food payment | C61: Food | D61: Expense | E61: 4800
A62: 13/1/2026 | B62: Micellaneous | C62: Others | D62: Income | E62: 2000
A63: 13/1/2026 | B63: Food payment | C63: Food | D63: Expense | E63: 1600
A64: 13/1/2026 | B64: Food payment | C64: Food | D64: Expense | E64: 1100
A65: 14/1/2026 | B65: Investment | C65: Investment | D65: Expense | E65: 5000
A66: 14/1/2026 | B66: Food payment | C66: Food | D66: Expense | E66: 1600
A67: 14/1/2026 | B67: Withdrawal | C67: Transport | D67: Expense | E67: 2100
A68: 22/1/2026 | B68: airtime | C68: Data | D68: Expense | E68: 200

Sheet Summary
A1: Category | B1: Actual expenses | C1: Budget | D1: variance
A2: Rent | B2: =SUMIFS(Transaction!E2:E68,Transaction!C2:C68,Summary!A2,Transaction!D2:D68,"Expense") -> 30000 | C2: =VLOOKUP(A2,Setup!A:B,2,FALSE) -> 30000 | D2: =C2-B2 -> 0
A3: Food | B3: =SUMIFS(Transaction!E3:E69,Transaction!C3:C69,Summary!A3,Transaction!D3:D69,"Expense") -> 70860 | C3: =VLOOKUP(A3,Setup!A:B,2,FALSE) -> 50000 | D3: =C3-B3 -> -20860
A4: Transport | B4: =SUMIFS(Transaction!E4:E70,Transaction!C4:C70,Summary!A4,Transaction!D4:D70,"Expense") -> 31600 | C4: =VLOOKUP(A4,Setup!A:B,2,FALSE) -> 45000 | D4: =C4-B4 -> 13400
A5: Utilities | B5: =SUMIFS(Transaction!E5:E71,Transaction!C5:C71,Summary!A5,Transaction!D5:D71,"Expense") -> 27700 | C5: 0 | D5: =C5-B5 -> -27700
A6: Data | B6: =SUMIFS(Transaction!E6:E72,Transaction!C6:C72,Summary!A6,Transaction!D6:D72,"Expense") -> 17200 | C6: =VLOOKUP(A6,Setup!A:B,2,FALSE) -> 2000 | D6: =C6-B6 -> -15200
A7: Entertainment | B7: =SUMIFS(Transaction!E7:E73,Transaction!C7:C73,Summary!A7,Transaction!D7:D73,"Expense") -> 20000 | C7: =VLOOKUP(A7,Setup!A:B,2,FALSE) -> 4500 | D7: =C7-B7 -> -15500
A8: Investment | B8: =SUMIFS(Transaction!E8:E74,Transaction!C8:C74,Summary!A8,Transaction!D8:D74,"Expense") -> 5000 | C8: =VLOOKUP(A8,Setup!A:B,2,FALSE) -> 10000 | D8: =C8-B8 -> 5000
A9: Parents | B9: =SUMIFS(Transaction!E9:E75,Transaction!C9:C75,Summary!A9,Transaction!D9:D75,"Expense") -> 10000 | C9: =VLOOKUP(A9,Setup!A:B,2,FALSE) -> 10000 | D9: =C9-B9 -> 0
A10: Savings | B10: =SUMIFS(Transaction!E10:E76,Transaction!C10:C76,Summary!A10,Transaction!D10:D76,"Expense") -> 0 | C10: 0 | D10: =C10-B10 -> 0
A11: Others | B11: =SUMIFS(Transaction!E11:E77,Transaction!C11:C77,Summary!A11,Transaction!D11:D77,"Expense") -> 43500 | C11: 0 | D11: =C11-B11 -> -43500
A14: FINANCIAL DASHBOARD
A16: Total income | B16: =SUMIFS(Transaction!E2:E68,Transaction!D2:D68,"income") -> 270300
A17: Total Expense | B17: =SUMIFS(Transaction!E2:E68,Transaction!D2:D68,"Expense") -> 266860
A18: Net balance | B18: =B16-B17 -> 3440
A21: Category | B21: Budget
A22: Rent | B22: 30000
A23: Food | B23: 50000
A24: Transport | B24: 45000
A25: Utilities | B25: 0
A26: Data | B26: 2000
A27: Entertainment | B27: 4500
A28: Investment | B28: 10000
A29: Parents | B29: 10000
A30: Savings | B30: 0
A31: Others | B31: 0
B43: Underutilized
B44: Category | C44: Unused amount
B45: Transport | C45: 13400
B46: Investment | C46: 5000
B48: Overutilized
B49: Category | C49: Overused amount
B50: Food | C50: -20860
B51: Utilities | C51: -27700
B52: Data | C52: -15200
B53: Entertainment | C53: -15500
B54: Others | C54: -43500
